sen2venus/__init__.py
sen2venus/dataset/__init__.py
sen2venus/dataset/sen2venus.py
sen2venus_pytorch_dataset-0.0.4.dist-info/LICENSE
sen2venus_pytorch_dataset-0.0.4.dist-info/METADATA
sen2venus_pytorch_dataset-0.0.4.dist-info/WHEEL
sen2venus_pytorch_dataset-0.0.4.dist-info/top_level.txt
sen2venus_pytorch_dataset-0.0.4.dist-info/RECORD
