Metadata-Version: 2.1
Name: sen2venus-pytorch-dataset
Version: 0.0.4
Summary: Unofficial pytorch dataloader for the Sen2Venµs Super-Resolution dataset.
Home-page: https://github.com/piclem/sen2venus-pytorch-dataset
Author: Clément Peyrard
Author-email: clement.peyrard.phd@gmail.com
License: MIT
License-File: LICENSE
Requires-Dist: torch
Requires-Dist: torchvision
Requires-Dist: rioxarray
Requires-Dist: py7zr
Requires-Dist: geopandas
Requires-Dist: fire
